{
  "info": {
    "name": "Implaner API",
    "schema": "https://schema.getpostman.com/json/collection/v2.1.0/collection.json",
    "version": "1.0.0",
    "description": "Postman collection for Implanner backend with auto token handling"
  },
  "item": [
    {
      "name": "Health",
      "request": {
        "method": "GET",
        "header": [],
        "url": {
          "raw": "{{baseUrl}}/health",
          "host": [
            "{{baseUrl}}"
          ],
          "path": [
            "health"
          ]
        }
      }
    },
    {
      "name": "Auth",
      "item": [
        {
          "name": "Register",
          "request": {
            "method": "POST",
            "header": [
              { "key": "Content-Type", "value": "application/json" }
            ],
            "body": {
              "mode": "raw",
              "raw": "{\n  \"email\": \"test.user+{{rand}}@example.com\",\n  \"password\": \"StrongP@ss1\",\n  \"name\": \"Test User\",\n  \"gdprConsent\": true,\n  \"kvkkConsent\": true\n}"
            },
            "url": { "raw": "{{baseUrl}}/api/auth/register", "host": ["{{baseUrl}}"], "path": ["api","auth","register"] }
          },
          "response": []
        },
        {
          "name": "Login",
          "event": [
            {
              "listen": "test",
              "script": {
                "exec": [
                  "if (pm.response.code === 200) {",
                  "  const json = pm.response.json();",
                  "  if (json && json.accessToken) {",
                  "    pm.environment.set('accessToken', json.accessToken);",
                  "  }",
                  "  if (json && json.user && json.user.id) {",
                  "    pm.environment.set('userId', json.user.id);",
                  "  }",
                  "}"
                ],
                "type": "text/javascript"
              }
            }
          ],
          "request": {
            "method": "POST",
            "header": [
              { "key": "Content-Type", "value": "application/json" }
            ],
            "body": {
              "mode": "raw",
              "raw": "{\n  \"email\": \"test.user@example.com\",\n  \"password\": \"StrongP@ss1\"\n}"
            },
            "url": { "raw": "{{baseUrl}}/api/auth/login", "host": ["{{baseUrl}}"], "path": ["api","auth","login"] }
          },
          "response": []
        },
        {
          "name": "Resend Verification Code",
          "request": {
            "method": "POST",
            "header": [ { "key": "Content-Type", "value": "application/json" } ],
            "body": { "mode": "raw", "raw": "{\n  \"email\": \"test.user@example.com\"\n}" },
            "url": { "raw": "{{baseUrl}}/api/auth/resend-code", "host": ["{{baseUrl}}"], "path": ["api","auth","resend-code"] }
          }
        },
        {
          "name": "Verify Email By Code",
          "request": {
            "method": "POST",
            "header": [ { "key": "Content-Type", "value": "application/json" } ],
            "body": { "mode": "raw", "raw": "{\n  \"email\": \"test.user@example.com\",\n  \"code\": \"123456\"\n}" },
            "url": { "raw": "{{baseUrl}}/api/auth/verify/code", "host": ["{{baseUrl}}"], "path": ["api","auth","verify","code"] }
          }
        },
        {
          "name": "Profile (requires auth)",
          "request": {
            "method": "GET",
            "header": [ { "key": "Authorization", "value": "Bearer {{accessToken}}" } ],
            "url": { "raw": "{{baseUrl}}/api/auth/profile", "host": ["{{baseUrl}}"], "path": ["api","auth","profile"] }
          }
        },
        {
          "name": "Google: Verify ID Token",
          "request": {
            "method": "POST",
            "header": [ { "key": "Content-Type", "value": "application/json" } ],
            "body": { "mode": "raw", "raw": "{\n  \"idToken\": \"<GOOGLE_ID_TOKEN>\"\n}" },
            "url": { "raw": "{{baseUrl}}/api/auth/google/id-token", "host": ["{{baseUrl}}"], "path": ["api","auth","google","id-token"] }
          }
        },
        {
          "name": "Google: Verify Access Token",
          "request": {
            "method": "POST",
            "header": [ { "key": "Content-Type", "value": "application/json" } ],
            "body": { "mode": "raw", "raw": "{\n  \"accessToken\": \"<GOOGLE_ACCESS_TOKEN>\"\n}" },
            "url": { "raw": "{{baseUrl}}/api/auth/google/access-token", "host": ["{{baseUrl}}"], "path": ["api","auth","google","access-token"] }
          }
        }
      ]
    },
    {
      "name": "Plans",
      "item": [
        {
          "name": "Create Plan (xray: analysisId)",
          "request": {
            "method": "POST",
            "header": [
              { "key": "Authorization", "value": "Bearer {{accessToken}}" },
              { "key": "Content-Type", "value": "application/json" }
            ],
            "body": {
              "mode": "raw",
              "raw": "{\n  \"userId\": {{userId}},\n  \"source\": \"xray\",\n  \"analysisId\": \"<CRANIOCATCH_ID>\",\n  \"budgetCents\": 50000,\n  \"questionnaire\": {\n    \"age\": 30,\n    \"boneLoss\": false,\n    \"smoking\": false,\n    \"chronicDiseases\": \"none\",\n    \"budgetPreference\": \"medium\",\n    \"medicalCondition\": \"none\"\n  }\n}"
            },
            "url": { "raw": "{{baseUrl}}/api/plans", "host": ["{{baseUrl}}"], "path": ["api","plans"] }
          }
        },
        {
          "name": "Create Plan (xray: xrayUrl as form-data)",
          "request": {
            "method": "POST",
            "header": [ { "key": "Authorization", "value": "Bearer {{accessToken}}" } ],
            "body": {
              "mode": "formdata",
              "formdata": [
                { "key": "userId", "value": "{{userId}}", "type": "text" },
                { "key": "source", "value": "xray", "type": "text" },
                { "key": "xrayUrl", "value": "https://example.com/xray.jpg", "type": "text" },
                { "key": "budgetCents", "value": "50000", "type": "text" },
                { "key": "questionnaire", "value": "{\"age\":30,\"boneLoss\":false}", "type": "text" }
              ]
            },
            "url": { "raw": "{{baseUrl}}/api/plans", "host": ["{{baseUrl}}"], "path": ["api","plans"] }
          },
          "description": "Note: Server expects JSON; form-data works for simple text fields. File upload is not implemented; use xrayUrl or analysisId."
        },
        {
          "name": "Create Plan (form source)",
          "request": {
            "method": "POST",
            "header": [
              { "key": "Authorization", "value": "Bearer {{accessToken}}" },
              { "key": "Content-Type", "value": "application/json" }
            ],
            "body": {
              "mode": "raw",
              "raw": "{\n  \"userId\": {{userId}},\n  \"source\": \"form\",\n  \"implants\": 2,\n  \"crowns\": 1,\n  \"fillings\": 3,\n  \"rootCanals\": 0,\n  \"budgetCents\": 40000,\n  \"questionnaire\": {\n    \"age\": 30,\n    \"smoking\": false\n  }\n}"
            },
            "url": { "raw": "{{baseUrl}}/api/plans", "host": ["{{baseUrl}}"], "path": ["api","plans"] }
          }
        },
        {
          "name": "Get Latest Plan By UserId",
          "request": {
            "method": "GET",
            "header": [ { "key": "Authorization", "value": "Bearer {{accessToken}}" } ],
            "url": { "raw": "{{baseUrl}}/api/plans/{{userId}}", "host": ["{{baseUrl}}"], "path": ["api","plans","{{userId}}"] }
          }
        },
        {
          "name": "Get Cloudinary Signature",
          "request": {
            "method": "GET",
            "header": [ { "key": "Authorization", "value": "Bearer {{accessToken}}" } ],
            "url": { "raw": "{{baseUrl}}/api/plans/cloudinary/signature", "host": ["{{baseUrl}}"], "path": ["api","plans","cloudinary","signature"] }
          }
        },
        {
          "name": "Analyze X-ray File (Minimal)",
          "request": {
            "method": "POST",
            "header": [ { "key": "Authorization", "value": "Bearer {{accessToken}}" } ],
            "body": {
              "mode": "formdata",
              "formdata": [
                { "key": "image", "type": "file", "src": [] },
                { "key": "rt_id", "value": "optional_rt_id", "type": "text" },
                { "key": "patient_id", "value": "optional_patient_id", "type": "text" }
              ]
            },
            "url": { "raw": "{{baseUrl}}/api/plans/analyze-minimal", "host": ["{{baseUrl}}"], "path": ["api","plans","analyze-minimal"] }
          }
        },
        {
          "name": "Generate Plan from CranioCatch ID",
          "request": {
            "method": "POST",
            "header": [
              { "key": "Authorization", "value": "Bearer {{accessToken}}" },
              { "key": "Content-Type", "value": "application/json" }
            ],
            "body": {
              "mode": "raw",
              "raw": "{\n  \"id\": \"<CRANIOCATCH_ANALYSIS_ID>\",\n  \"userId\": {{userId}}\n}"
            },
            "url": { "raw": "{{baseUrl}}/api/plans/generate-plan", "host": ["{{baseUrl}}"], "path": ["api","plans","generate-plan"] }
          }
        },
        {
          "name": "Get All Plans By User",
          "request": {
            "method": "GET",
            "header": [ { "key": "Authorization", "value": "Bearer {{accessToken}}" } ],
            "url": { "raw": "{{baseUrl}}/api/plans/user/all?userId={{userId}}", "host": ["{{baseUrl}}"], "path": ["api","plans","user","all"], "query": [ { "key": "userId", "value": "{{userId}}" } ] }
          }
        },
        {
          "name": "Get Plan By Plan ID",
          "request": {
            "method": "GET",
            "header": [ { "key": "Authorization", "value": "Bearer {{accessToken}}" } ],
            "url": { "raw": "{{baseUrl}}/api/plans/plan/1", "host": ["{{baseUrl}}"], "path": ["api","plans","plan","1"] }
          }
        }
      ]
    }
  ],
  "event": [],
  "variable": [
    { "key": "baseUrl", "value": "http://localhost:8080" },
    { "key": "accessToken", "value": "" },
    { "key": "userId", "value": "1" },
    { "key": "rand", "value": "{{$randomInt}}" }
  ]
}


